impactlab_user/__init__.py
impactlab_user/cli.py
impactlab_user/datafs/config.yml
impactlab_user-0.1.8.dist-info/DESCRIPTION.rst
impactlab_user-0.1.8.dist-info/METADATA
impactlab_user-0.1.8.dist-info/RECORD
impactlab_user-0.1.8.dist-info/WHEEL
impactlab_user-0.1.8.dist-info/entry_points.txt
impactlab_user-0.1.8.dist-info/metadata.json
impactlab_user-0.1.8.dist-info/top_level.txt
