Metadata-Version: 2.0
Name: impactlab-user
Version: 0.1.8
Summary: Set up users to use Climate Impact Lab tools
Home-page: https://github.com/ClimateImpactLab/impactlab_user
Author: Climate Impact Lab
Author-email: UNKNOWN
License: MIT license
Keywords: impactlab_user
Platform: UNKNOWN
Classifier: Development Status :: 2 - Pre-Alpha
Classifier: Intended Audience :: Developers
Classifier: License :: OSI Approved :: MIT License
Classifier: Natural Language :: English
Classifier: Programming Language :: Python :: 2
Classifier: Programming Language :: Python :: 2.7
Requires-Dist: PyYAML (>=3.10)
Requires-Dist: Sphinx (>=1.4.1)
Requires-Dist: boto (>=2.30.0)
Requires-Dist: boto3 (>=1.0)
Requires-Dist: click (>=6.0)
Requires-Dist: datafs (>=0.6.9)
Requires-Dist: impactlab-tools (>=0.0.3)
Requires-Dist: jinja2 (>=2.8)
Requires-Dist: sphinx-rtd-theme (>=0.1.0)
Provides-Extra: test
Requires-Dist: PyYAML (>=3.10); extra == 'test'
Requires-Dist: Sphinx (>=1.4.1); extra == 'test'
Requires-Dist: boto (>=2.30.0); extra == 'test'
Requires-Dist: boto3 (>=1.0); extra == 'test'
Requires-Dist: click (>=6.0); extra == 'test'
Requires-Dist: coverage (>=4.0); extra == 'test'
Requires-Dist: datafs (>=0.6.9); extra == 'test'
Requires-Dist: flake8 (>=2.0); extra == 'test'
Requires-Dist: impactlab-tools (>=0.0.3); extra == 'test'
Requires-Dist: jinja2 (>=2.8); extra == 'test'
Requires-Dist: pip (>=8.0); extra == 'test'
Requires-Dist: pytest (>=3.0); extra == 'test'
Requires-Dist: pytest-cov (>=2.0); extra == 'test'
Requires-Dist: pytest-runner (>=2.5); extra == 'test'
Requires-Dist: sphinx-rtd-theme (>=0.1.0); extra == 'test'
Requires-Dist: tox (>=2.3.0); extra == 'test'
Requires-Dist: wheel (>=0.27); extra == 'test'
